<?xml version="1.0"?>
<testResults>
  <FitNesseVersion>v20100403</FitNesseVersion>
  <rootPath>ProgrammingExample</rootPath>
    <result>
    <counts>
      <right>1</right>
      <wrong>0</wrong>
      <ignores>0</ignores>
      <exceptions>14</exceptions>
    </counts>
    <content><![CDATA[<table border="1" cellspacing="0" _TABLENUMBER=9188318347775032136>
<tr><td>import</td>
</tr>
<tr><td>com.statefarm.rpn.fixtures</td>
</tr>
</table>
<br/><table border="1" cellspacing="0" _TABLENUMBER=6042231254458337778>
<tr><td>scenario</td>
<td>Given an RpnCalculator</td>
</tr>
<tr><td colspan="2">reset calculator</td>
</tr>
</table>
<br/><table border="1" cellspacing="0" _TABLENUMBER=554332078078728203>
<tr><td>scenario</td>
<td>When creating a program</td>
</tr>
<tr><td colspan="2">start program</td>
</tr>
</table>
<br/><table border="1" cellspacing="0" _TABLENUMBER=5363126168719825884>
<tr><td>scenario</td>
<td>with operator _</td>
<td>operatorName</td>
</tr>
<tr><td>add to program</td>
<td colspan="2">@operatorName</td>
</tr>
</table>
<br/><table border="1" cellspacing="0" _TABLENUMBER=7658557999944145192>
<tr><td>scenario</td>
<td>and operator _</td>
<td>operatorName</td>
</tr>
</table>
|with operator<br/><table border="1" cellspacing="0" _TABLENUMBER=7697975284390046002>
<tr><td>scenario</td>
<td>and then saving that as _</td>
<td>operatorName</td>
</tr>
<tr><td>save program as</td>
<td colspan="2">@operatorName</td>
</tr>
</table>
<br/><table border="1" cellspacing="0" _TABLENUMBER=1873082332870578983>
<tr><td>scenario</td>
<td>Then the operator _ should be found</td>
<td>operatorName</td>
</tr>
<tr><td>check</td>
<td>operator exists</td>
<td>@operatorName</td>
</tr>
</table>
<br/><table border="1" cellspacing="0" _TABLENUMBER=4558500375031044349>
<tr><td>scenario</td>
<td>Given the previous RpnCalculator</td>
</tr>
<tr><td colspan="2">use existing calculator</td>
</tr>
</table>
<br/><table border="1" cellspacing="0" _TABLENUMBER=8977308254735995972>
<tr><td>scenario</td>
<td>and then entering _</td>
<td>value</td>
</tr>
<tr><td>enter</td>
<td colspan="2">@value</td>
</tr>
</table>
<br/><table border="1" cellspacing="0" _TABLENUMBER=6379225029598195222>
<tr><td>scenario</td>
<td>When executing _</td>
<td>operatorName</td>
</tr>
<tr><td>execute</td>
<td colspan="2">@operatorName</td>
</tr>
</table>
<br/><table border="1" cellspacing="0" _TABLENUMBER=307933207359642534>
<tr><td>scenario</td>
<td>Then the result should be _</td>
<td>expected</td>
</tr>
<tr><td>check</td>
<td>xRegister</td>
<td>@expected</td>
</tr>
</table>
<br/><table border="1" cellspacing="0" _TABLENUMBER=495239805102537416>
<tr><td>script</td>
<td><span class="pass">RpnCalculatorFixture</span></td>
</tr>
</table>
<br/><table class="plain_text_table" _TABLENUMBER=3456507470819754814><tr class="hidden"><td>script</td>
</tr>
<tr><td class=pass>Given an RpnCalculator</td>
<TD class=pass><div class="collapse_rim">
	<a href="javascript:toggleCollapsable('6917050081558655647');">
		<img src="/files/images/collapsableClosed.gif" class="left" id="img6917050081558655647"/>
	</a>
	<span id="test_status" class=pass>Scenario</span>
	<div class="hidden" id="6917050081558655647"><table border="1" cellspacing="0" _TABLENUMBER=1244786567379945136 table_name="scriptTable_12_0/scriptTable_1">
<tr><td>scenario</td>
<td>Given an RpnCalculator</td>
</tr>
<tr><td colspan="2">reset calculator</td>
</tr>
</table></div>
</div></TD></tr>
<tr><td class=pass>When creating a program</td>
<TD class=pass><div class="collapse_rim">
	<a href="javascript:toggleCollapsable('8254354434893440462');">
		<img src="/files/images/collapsableClosed.gif" class="left" id="img8254354434893440462"/>
	</a>
	<span id="test_status" class=pass>Scenario</span>
	<div class="hidden" id="8254354434893440462"><table border="1" cellspacing="0" _TABLENUMBER=1281922379441748181 table_name="scriptTable_12_1/scriptTable_2">
<tr><td>scenario</td>
<td>When creating a program</td>
</tr>
<tr><td colspan="2">start program</td>
</tr>
</table></div>
</div></TD></tr>
<tr><td class=pass>with operator _+</td>
<TD class=pass><div class="collapse_rim">
	<a href="javascript:toggleCollapsable('-3545714057842430995');">
		<img src="/files/images/collapsableClosed.gif" class="left" id="img-3545714057842430995"/>
	</a>
	<span id="test_status" class=pass>Scenario</span>
	<div class="hidden" id="-3545714057842430995"><table border="1" cellspacing="0" _TABLENUMBER=2742028842405208672 table_name="scriptTable_12_2/scriptTable_3">
<tr><td>scenario</td>
<td>with operator _</td>
<td>operatorName</td>
</tr>
<tr><td>add to program</td>
<td colspan="2">_+</td>
</tr>
</table></div>
</div></TD></tr>
<tr><td class=pass>and operator _/</td>
<TD class=pass><div class="collapse_rim">
	<a href="javascript:toggleCollapsable('1513044783160069252');">
		<img src="/files/images/collapsableClosed.gif" class="left" id="img1513044783160069252"/>
	</a>
	<span id="test_status" class=pass>Scenario</span>
	<div class="hidden" id="1513044783160069252"><table border="1" cellspacing="0" _TABLENUMBER=614976362545739816 table_name="scriptTable_12_3/scriptTable_4">
<tr><td>scenario</td>
<td>and operator _</td>
<td>operatorName</td>
</tr>
</table></div>
</div></TD></tr>
<tr><td class=pass>and then saving that as _+/</td>
<TD class=pass><div class="collapse_rim">
	<a href="javascript:toggleCollapsable('920928524548513562');">
		<img src="/files/images/collapsableClosed.gif" class="left" id="img920928524548513562"/>
	</a>
	<span id="test_status" class=pass>Scenario</span>
	<div class="hidden" id="920928524548513562"><table border="1" cellspacing="0" _TABLENUMBER=3909173723454989030 table_name="scriptTable_12_4/scriptTable_5">
<tr><td>scenario</td>
<td>and then saving that as _</td>
<td>operatorName</td>
</tr>
<tr><td>save program as</td>
<td colspan="2">_+/</td>
</tr>
</table></div>
</div></TD></tr>
<tr><td class=fail>Then the operator _+/ should be found</td>
<TD class=fail><div class="collapse_rim">
	<a href="javascript:toggleCollapsable('2770448832891642057');">
		<img src="/files/images/collapsableClosed.gif" class="left" id="img2770448832891642057"/>
	</a>
	<span id="test_status" class=fail>Scenario</span>
	<div class="hidden" id="2770448832891642057"><table border="1" cellspacing="0" _TABLENUMBER=6785295580502049917 table_name="scriptTable_12_5/scriptTable_6">
<tr><td>scenario</td>
<td>Then the operator _ should be found</td>
<td>operatorName</td>
</tr>
<tr><td>check</td>
<td>operator exists</td>
<td>_+/ <span class="error">Method operatorExists[0] not found in com.statefarm.rpn.fixtures.RpnCalculatorFixture.</span></td>
</tr>
</table></div>
</div></TD></tr>
</table><br/><table class="plain_text_table" _TABLENUMBER=5817907022548492120><tr class="hidden"><td>script</td>
</tr>
<tr><td class=fail>Given the previous RpnCalculator</td>
<TD class=fail><div class="collapse_rim">
	<a href="javascript:toggleCollapsable('-3794277777817426727');">
		<img src="/files/images/collapsableClosed.gif" class="left" id="img-3794277777817426727"/>
	</a>
	<span id="test_status" class=fail>Scenario</span>
	<div class="hidden" id="-3794277777817426727"><table border="1" cellspacing="0" _TABLENUMBER=4585506804504739072 table_name="scriptTable_13_0/scriptTable_7">
<tr><td>scenario</td>
<td>Given the previous RpnCalculator</td>
</tr>
<tr><td colspan="2">use existing calculator <span class="error">Method useExistingCalculator[0] not found in com.statefarm.rpn.fixtures.RpnCalculatorFixture.</span></td>
</tr>
</table></div>
</div></TD></tr>
<tr><td class=fail>and then entering 4</td>
<TD class=fail><div class="collapse_rim">
	<a href="javascript:toggleCollapsable('5538441050510167322');">
		<img src="/files/images/collapsableClosed.gif" class="left" id="img5538441050510167322"/>
	</a>
	<span id="test_status" class=fail>Scenario</span>
	<div class="hidden" id="5538441050510167322"><table border="1" cellspacing="0" _TABLENUMBER=2525693451820617542 table_name="scriptTable_13_1/scriptTable_8">
<tr><td>scenario</td>
<td>and then entering _</td>
<td>value</td>
</tr>
<tr><td>enter <span class="error">Method enter[1] not found in com.statefarm.rpn.fixtures.RpnCalculatorFixture.</span></td>
<td colspan="2">4</td>
</tr>
</table></div>
</div></TD></tr>
<tr><td>and 7 <span class="error">Method and7[0] not found in com.statefarm.rpn.fixtures.RpnCalculatorFixture.</span></td>
</tr>
<tr><td>and 9 <span class="error">Method and9[0] not found in com.statefarm.rpn.fixtures.RpnCalculatorFixture.</span></td>
</tr>
<tr><td class=fail>When executing _+/</td>
<TD class=fail><div class="collapse_rim">
	<a href="javascript:toggleCollapsable('-9029736009689894690');">
		<img src="/files/images/collapsableClosed.gif" class="left" id="img-9029736009689894690"/>
	</a>
	<span id="test_status" class=fail>Scenario</span>
	<div class="hidden" id="-9029736009689894690"><table border="1" cellspacing="0" _TABLENUMBER=4068560916759317803 table_name="scriptTable_13_4/scriptTable_9">
<tr><td>scenario</td>
<td>When executing _</td>
<td>operatorName</td>
</tr>
<tr><td>execute <span class="error">Method execute[1] not found in com.statefarm.rpn.fixtures.RpnCalculatorFixture.</span></td>
<td colspan="2">_+/</td>
</tr>
</table></div>
</div></TD></tr>
<tr><td class=fail>Then the result should be 0.25</td>
<TD class=fail><div class="collapse_rim">
	<a href="javascript:toggleCollapsable('5402255779855815845');">
		<img src="/files/images/collapsableClosed.gif" class="left" id="img5402255779855815845"/>
	</a>
	<span id="test_status" class=fail>Scenario</span>
	<div class="hidden" id="5402255779855815845"><table border="1" cellspacing="0" _TABLENUMBER=6287085305831200539 table_name="scriptTable_13_5/scriptTable_10">
<tr><td>scenario</td>
<td>Then the result should be _</td>
<td>expected</td>
</tr>
<tr><td>check</td>
<td>xRegister</td>
<td>0.25 <span class="error">Method xRegister[0] not found in com.statefarm.rpn.fixtures.RpnCalculatorFixture.</span></td>
</tr>
</table></div>
</div></TD></tr>
</table>]]></content>
    <relativePageName>ProgrammingExample</relativePageName>
    
        <tables>
            <table>
        <name>import_0</name>
                <row>
                    <col><![CDATA[import]]></col>
          
        </row>
                <row>
                    <col><![CDATA[com.statefarm.rpn.fixtures]]></col>
          
        </row>
        
      </table>
            <table>
        <name>scenarioTable_1</name>
                <row>
                    <col><![CDATA[scenario]]></col>
                    <col><![CDATA[Given an RpnCalculator]]></col>
          
        </row>
                <row>
                    <col><![CDATA[reset calculator]]></col>
          
        </row>
        
      </table>
            <table>
        <name>scenarioTable_2</name>
                <row>
                    <col><![CDATA[scenario]]></col>
                    <col><![CDATA[When creating a program]]></col>
          
        </row>
                <row>
                    <col><![CDATA[start program]]></col>
          
        </row>
        
      </table>
            <table>
        <name>scenarioTable_3</name>
                <row>
                    <col><![CDATA[scenario]]></col>
                    <col><![CDATA[with operator _]]></col>
                    <col><![CDATA[operatorName]]></col>
          
        </row>
                <row>
                    <col><![CDATA[add to program]]></col>
                    <col><![CDATA[@operatorName]]></col>
          
        </row>
        
      </table>
            <table>
        <name>scenarioTable_4</name>
                <row>
                    <col><![CDATA[scenario]]></col>
                    <col><![CDATA[and operator _]]></col>
                    <col><![CDATA[operatorName]]></col>
          
        </row>
        
      </table>
            <table>
        <name>scenarioTable_5</name>
                <row>
                    <col><![CDATA[scenario]]></col>
                    <col><![CDATA[and then saving that as _]]></col>
                    <col><![CDATA[operatorName]]></col>
          
        </row>
                <row>
                    <col><![CDATA[save program as]]></col>
                    <col><![CDATA[@operatorName]]></col>
          
        </row>
        
      </table>
            <table>
        <name>scenarioTable_6</name>
                <row>
                    <col><![CDATA[scenario]]></col>
                    <col><![CDATA[Then the operator _ should be found]]></col>
                    <col><![CDATA[operatorName]]></col>
          
        </row>
                <row>
                    <col><![CDATA[check]]></col>
                    <col><![CDATA[operator exists]]></col>
                    <col><![CDATA[@operatorName]]></col>
          
        </row>
        
      </table>
            <table>
        <name>scenarioTable_7</name>
                <row>
                    <col><![CDATA[scenario]]></col>
                    <col><![CDATA[Given the previous RpnCalculator]]></col>
          
        </row>
                <row>
                    <col><![CDATA[use existing calculator]]></col>
          
        </row>
        
      </table>
            <table>
        <name>scenarioTable_8</name>
                <row>
                    <col><![CDATA[scenario]]></col>
                    <col><![CDATA[and then entering _]]></col>
                    <col><![CDATA[value]]></col>
          
        </row>
                <row>
                    <col><![CDATA[enter]]></col>
                    <col><![CDATA[@value]]></col>
          
        </row>
        
      </table>
            <table>
        <name>scenarioTable_9</name>
                <row>
                    <col><![CDATA[scenario]]></col>
                    <col><![CDATA[When executing _]]></col>
                    <col><![CDATA[operatorName]]></col>
          
        </row>
                <row>
                    <col><![CDATA[execute]]></col>
                    <col><![CDATA[@operatorName]]></col>
          
        </row>
        
      </table>
            <table>
        <name>scenarioTable_10</name>
                <row>
                    <col><![CDATA[scenario]]></col>
                    <col><![CDATA[Then the result should be _]]></col>
                    <col><![CDATA[expected]]></col>
          
        </row>
                <row>
                    <col><![CDATA[check]]></col>
                    <col><![CDATA[xRegister]]></col>
                    <col><![CDATA[@expected]]></col>
          
        </row>
        
      </table>
            <table>
        <name>scriptTable_11</name>
                <row>
                    <col><![CDATA[script]]></col>
                    <col><![CDATA[pass(RpnCalculatorFixture)]]></col>
          
        </row>
        
      </table>
            <table>
        <name>scriptTable_12</name>
                <row>
                    <col><![CDATA[script]]></col>
          
        </row>
                <row>
                    <col><![CDATA[Given an RpnCalculator]]></col>
                    <col><![CDATA[pass(scenario:scriptTable_12_0/scriptTable_1)]]></col>
          
        </row>
                <row>
                    <col><![CDATA[When creating a program]]></col>
                    <col><![CDATA[pass(scenario:scriptTable_12_1/scriptTable_2)]]></col>
          
        </row>
                <row>
                    <col><![CDATA[with operator _+]]></col>
                    <col><![CDATA[pass(scenario:scriptTable_12_2/scriptTable_3)]]></col>
          
        </row>
                <row>
                    <col><![CDATA[and operator _/]]></col>
                    <col><![CDATA[pass(scenario:scriptTable_12_3/scriptTable_4)]]></col>
          
        </row>
                <row>
                    <col><![CDATA[and then saving that as _+/]]></col>
                    <col><![CDATA[pass(scenario:scriptTable_12_4/scriptTable_5)]]></col>
          
        </row>
                <row>
                    <col><![CDATA[Then the operator _+/ should be found]]></col>
                    <col><![CDATA[fail(scenario:scriptTable_12_5/scriptTable_6)]]></col>
          
        </row>
        
      </table>
            <table>
        <name>scriptTable_12_0/scriptTable_1</name>
                <row>
                    <col><![CDATA[scenario]]></col>
                    <col><![CDATA[Given an RpnCalculator]]></col>
          
        </row>
                <row>
                    <col><![CDATA[reset calculator]]></col>
          
        </row>
        
      </table>
            <table>
        <name>scriptTable_12_1/scriptTable_2</name>
                <row>
                    <col><![CDATA[scenario]]></col>
                    <col><![CDATA[When creating a program]]></col>
          
        </row>
                <row>
                    <col><![CDATA[start program]]></col>
          
        </row>
        
      </table>
            <table>
        <name>scriptTable_12_2/scriptTable_3</name>
                <row>
                    <col><![CDATA[scenario]]></col>
                    <col><![CDATA[with operator _]]></col>
                    <col><![CDATA[operatorName]]></col>
          
        </row>
                <row>
                    <col><![CDATA[add to program]]></col>
                    <col><![CDATA[_+]]></col>
          
        </row>
        
      </table>
            <table>
        <name>scriptTable_12_3/scriptTable_4</name>
                <row>
                    <col><![CDATA[scenario]]></col>
                    <col><![CDATA[and operator _]]></col>
                    <col><![CDATA[operatorName]]></col>
          
        </row>
        
      </table>
            <table>
        <name>scriptTable_12_4/scriptTable_5</name>
                <row>
                    <col><![CDATA[scenario]]></col>
                    <col><![CDATA[and then saving that as _]]></col>
                    <col><![CDATA[operatorName]]></col>
          
        </row>
                <row>
                    <col><![CDATA[save program as]]></col>
                    <col><![CDATA[_+/]]></col>
          
        </row>
        
      </table>
            <table>
        <name>scriptTable_12_5/scriptTable_6</name>
                <row>
                    <col><![CDATA[scenario]]></col>
                    <col><![CDATA[Then the operator _ should be found]]></col>
                    <col><![CDATA[operatorName]]></col>
          
        </row>
                <row>
                    <col><![CDATA[check]]></col>
                    <col><![CDATA[operator exists]]></col>
                    <col><![CDATA[_+/ error(Method operatorExists[0] not found in com.statefarm.rpn.fixtures.RpnCalculatorFixture.)]]></col>
          
        </row>
        
      </table>
            <table>
        <name>scriptTable_13</name>
                <row>
                    <col><![CDATA[script]]></col>
          
        </row>
                <row>
                    <col><![CDATA[Given the previous RpnCalculator]]></col>
                    <col><![CDATA[fail(scenario:scriptTable_13_0/scriptTable_7)]]></col>
          
        </row>
                <row>
                    <col><![CDATA[and then entering 4]]></col>
                    <col><![CDATA[fail(scenario:scriptTable_13_1/scriptTable_8)]]></col>
          
        </row>
                <row>
                    <col><![CDATA[and 7 error(Method and7[0] not found in com.statefarm.rpn.fixtures.RpnCalculatorFixture.)]]></col>
          
        </row>
                <row>
                    <col><![CDATA[and 9 error(Method and9[0] not found in com.statefarm.rpn.fixtures.RpnCalculatorFixture.)]]></col>
          
        </row>
                <row>
                    <col><![CDATA[When executing _+/]]></col>
                    <col><![CDATA[fail(scenario:scriptTable_13_4/scriptTable_9)]]></col>
          
        </row>
                <row>
                    <col><![CDATA[Then the result should be 0.25]]></col>
                    <col><![CDATA[fail(scenario:scriptTable_13_5/scriptTable_10)]]></col>
          
        </row>
        
      </table>
            <table>
        <name>scriptTable_13_0/scriptTable_7</name>
                <row>
                    <col><![CDATA[scenario]]></col>
                    <col><![CDATA[Given the previous RpnCalculator]]></col>
          
        </row>
                <row>
                    <col><![CDATA[use existing calculator error(Method useExistingCalculator[0] not found in com.statefarm.rpn.fixtures.RpnCalculatorFixture.)]]></col>
          
        </row>
        
      </table>
            <table>
        <name>scriptTable_13_1/scriptTable_8</name>
                <row>
                    <col><![CDATA[scenario]]></col>
                    <col><![CDATA[and then entering _]]></col>
                    <col><![CDATA[value]]></col>
          
        </row>
                <row>
                    <col><![CDATA[enter error(Method enter[1] not found in com.statefarm.rpn.fixtures.RpnCalculatorFixture.)]]></col>
                    <col><![CDATA[4]]></col>
          
        </row>
        
      </table>
            <table>
        <name>scriptTable_13_4/scriptTable_9</name>
                <row>
                    <col><![CDATA[scenario]]></col>
                    <col><![CDATA[When executing _]]></col>
                    <col><![CDATA[operatorName]]></col>
          
        </row>
                <row>
                    <col><![CDATA[execute error(Method execute[1] not found in com.statefarm.rpn.fixtures.RpnCalculatorFixture.)]]></col>
                    <col><![CDATA[_+/]]></col>
          
        </row>
        
      </table>
            <table>
        <name>scriptTable_13_5/scriptTable_10</name>
                <row>
                    <col><![CDATA[scenario]]></col>
                    <col><![CDATA[Then the result should be _]]></col>
                    <col><![CDATA[expected]]></col>
          
        </row>
                <row>
                    <col><![CDATA[check]]></col>
                    <col><![CDATA[xRegister]]></col>
                    <col><![CDATA[0.25 error(Method xRegister[0] not found in com.statefarm.rpn.fixtures.RpnCalculatorFixture.)]]></col>
          
        </row>
        
      </table>
      
    </tables>
    
    
    <instructions>
            <instructionResult>
        <instruction><![CDATA[[import_0_0, import, com.statefarm.rpn.fixtures]]]></instruction>
        <slimResult><![CDATA[OK]]></slimResult>
        
      </instructionResult>
            <instructionResult>
        <instruction><![CDATA[[scriptTable_11_0, make, scriptTableActor, RpnCalculatorFixture]]]></instruction>
        <slimResult><![CDATA[OK]]></slimResult>
                <expectation>
          <status>right</status>
          <instructionId>scriptTable_11_0</instructionId>
          <col>1</col>
          <row>0</row>
          <type>ConstructionExpectation</type>
                    <actual><![CDATA[OK]]></actual>
                              <expected><![CDATA[RpnCalculatorFixture]]></expected>
                              <evaluationMessage><![CDATA[pass(RpnCalculatorFixture)]]></evaluationMessage>
                  </expectation>
        
      </instructionResult>
            <instructionResult>
        <instruction><![CDATA[[scriptTable_12_0/scriptTable_1_0, call, scriptTableActor, resetCalculator]]]></instruction>
        <slimResult><![CDATA[/__VOID__/]]></slimResult>
                <expectation>
          <status>ignored</status>
          <instructionId>scriptTable_12_0/scriptTable_1_0</instructionId>
          <col>0</col>
          <row>1</row>
          <type>ScriptActionExpectation</type>
                    <actual><![CDATA[/__VOID__/]]></actual>
                              <expected><![CDATA[reset calculator]]></expected>
                              <evaluationMessage><![CDATA[reset calculator]]></evaluationMessage>
                  </expectation>
        
      </instructionResult>
            <instructionResult>
        <instruction><![CDATA[[scriptTable_12_1/scriptTable_2_0, call, scriptTableActor, startProgram]]]></instruction>
        <slimResult><![CDATA[/__VOID__/]]></slimResult>
                <expectation>
          <status>ignored</status>
          <instructionId>scriptTable_12_1/scriptTable_2_0</instructionId>
          <col>0</col>
          <row>1</row>
          <type>ScriptActionExpectation</type>
                    <actual><![CDATA[/__VOID__/]]></actual>
                              <expected><![CDATA[start program]]></expected>
                              <evaluationMessage><![CDATA[start program]]></evaluationMessage>
                  </expectation>
        
      </instructionResult>
            <instructionResult>
        <instruction><![CDATA[[scriptTable_12_2/scriptTable_3_0, call, scriptTableActor, addToProgram, _+]]]></instruction>
        <slimResult><![CDATA[/__VOID__/]]></slimResult>
                <expectation>
          <status>ignored</status>
          <instructionId>scriptTable_12_2/scriptTable_3_0</instructionId>
          <col>1</col>
          <row>1</row>
          <type>ArgumentExpectation</type>
                                        <evaluationMessage><![CDATA[]]></evaluationMessage>
                  </expectation>
                <expectation>
          <status>ignored</status>
          <instructionId>scriptTable_12_2/scriptTable_3_0</instructionId>
          <col>0</col>
          <row>1</row>
          <type>ScriptActionExpectation</type>
                    <actual><![CDATA[/__VOID__/]]></actual>
                              <expected><![CDATA[add to program]]></expected>
                              <evaluationMessage><![CDATA[add to program]]></evaluationMessage>
                  </expectation>
        
      </instructionResult>
            <instructionResult>
        <instruction><![CDATA[[scriptTable_12_4/scriptTable_5_0, call, scriptTableActor, saveProgramAs, _+/]]]></instruction>
        <slimResult><![CDATA[/__VOID__/]]></slimResult>
                <expectation>
          <status>ignored</status>
          <instructionId>scriptTable_12_4/scriptTable_5_0</instructionId>
          <col>1</col>
          <row>1</row>
          <type>ArgumentExpectation</type>
                                        <evaluationMessage><![CDATA[]]></evaluationMessage>
                  </expectation>
                <expectation>
          <status>ignored</status>
          <instructionId>scriptTable_12_4/scriptTable_5_0</instructionId>
          <col>0</col>
          <row>1</row>
          <type>ScriptActionExpectation</type>
                    <actual><![CDATA[/__VOID__/]]></actual>
                              <expected><![CDATA[save program as]]></expected>
                              <evaluationMessage><![CDATA[save program as]]></evaluationMessage>
                  </expectation>
        
      </instructionResult>
            <instructionResult>
        <instruction><![CDATA[[scriptTable_12_5/scriptTable_6_0, call, scriptTableActor, operatorExists]]]></instruction>
        <slimResult><![CDATA[!error:Method operatorExists[0] not found in com.statefarm.rpn.fixtures.RpnCalculatorFixture.]]></slimResult>
                <expectation>
          <status>ignored</status>
          <instructionId>scriptTable_12_5/scriptTable_6_0</instructionId>
          <col>2</col>
          <row>1</row>
          <type>ReturnedValueExpectation</type>
                    <actual><![CDATA[!error:Method operatorExists[0] not found in com.statefarm.rpn.fixtures.RpnCalculatorFixture.]]></actual>
                              <expected><![CDATA[_+/]]></expected>
                              <evaluationMessage><![CDATA[_+/ error(Method operatorExists[0] not found in com.statefarm.rpn.fixtures.RpnCalculatorFixture.)]]></evaluationMessage>
                  </expectation>
        
      </instructionResult>
            <instructionResult>
        <instruction><![CDATA[[scriptTable_13_0/scriptTable_7_0, call, scriptTableActor, useExistingCalculator]]]></instruction>
        <slimResult><![CDATA[!error:Method useExistingCalculator[0] not found in com.statefarm.rpn.fixtures.RpnCalculatorFixture.]]></slimResult>
                <expectation>
          <status>ignored</status>
          <instructionId>scriptTable_13_0/scriptTable_7_0</instructionId>
          <col>0</col>
          <row>1</row>
          <type>ScriptActionExpectation</type>
                    <actual><![CDATA[!error:Method useExistingCalculator[0] not found in com.statefarm.rpn.fixtures.RpnCalculatorFixture.]]></actual>
                              <expected><![CDATA[use existing calculator]]></expected>
                              <evaluationMessage><![CDATA[use existing calculator error(Method useExistingCalculator[0] not found in com.statefarm.rpn.fixtures.RpnCalculatorFixture.)]]></evaluationMessage>
                  </expectation>
        
      </instructionResult>
            <instructionResult>
        <instruction><![CDATA[[scriptTable_13_1/scriptTable_8_0, call, scriptTableActor, enter, 4]]]></instruction>
        <slimResult><![CDATA[!error:Method enter[1] not found in com.statefarm.rpn.fixtures.RpnCalculatorFixture.]]></slimResult>
                <expectation>
          <status>ignored</status>
          <instructionId>scriptTable_13_1/scriptTable_8_0</instructionId>
          <col>1</col>
          <row>1</row>
          <type>ArgumentExpectation</type>
                                        <evaluationMessage><![CDATA[]]></evaluationMessage>
                  </expectation>
                <expectation>
          <status>ignored</status>
          <instructionId>scriptTable_13_1/scriptTable_8_0</instructionId>
          <col>0</col>
          <row>1</row>
          <type>ScriptActionExpectation</type>
                    <actual><![CDATA[!error:Method enter[1] not found in com.statefarm.rpn.fixtures.RpnCalculatorFixture.]]></actual>
                              <expected><![CDATA[enter]]></expected>
                              <evaluationMessage><![CDATA[enter error(Method enter[1] not found in com.statefarm.rpn.fixtures.RpnCalculatorFixture.)]]></evaluationMessage>
                  </expectation>
        
      </instructionResult>
            <instructionResult>
        <instruction><![CDATA[[scriptTable_13_2, call, scriptTableActor, and7]]]></instruction>
        <slimResult><![CDATA[!error:Method and7[0] not found in com.statefarm.rpn.fixtures.RpnCalculatorFixture.]]></slimResult>
                <expectation>
          <status>ignored</status>
          <instructionId>scriptTable_13_2</instructionId>
          <col>0</col>
          <row>3</row>
          <type>ScriptActionExpectation</type>
                    <actual><![CDATA[!error:Method and7[0] not found in com.statefarm.rpn.fixtures.RpnCalculatorFixture.]]></actual>
                              <expected><![CDATA[and 7]]></expected>
                              <evaluationMessage><![CDATA[and 7 error(Method and7[0] not found in com.statefarm.rpn.fixtures.RpnCalculatorFixture.)]]></evaluationMessage>
                  </expectation>
        
      </instructionResult>
            <instructionResult>
        <instruction><![CDATA[[scriptTable_13_3, call, scriptTableActor, and9]]]></instruction>
        <slimResult><![CDATA[!error:Method and9[0] not found in com.statefarm.rpn.fixtures.RpnCalculatorFixture.]]></slimResult>
                <expectation>
          <status>ignored</status>
          <instructionId>scriptTable_13_3</instructionId>
          <col>0</col>
          <row>4</row>
          <type>ScriptActionExpectation</type>
                    <actual><![CDATA[!error:Method and9[0] not found in com.statefarm.rpn.fixtures.RpnCalculatorFixture.]]></actual>
                              <expected><![CDATA[and 9]]></expected>
                              <evaluationMessage><![CDATA[and 9 error(Method and9[0] not found in com.statefarm.rpn.fixtures.RpnCalculatorFixture.)]]></evaluationMessage>
                  </expectation>
        
      </instructionResult>
            <instructionResult>
        <instruction><![CDATA[[scriptTable_13_4/scriptTable_9_0, call, scriptTableActor, execute, _+/]]]></instruction>
        <slimResult><![CDATA[!error:Method execute[1] not found in com.statefarm.rpn.fixtures.RpnCalculatorFixture.]]></slimResult>
                <expectation>
          <status>ignored</status>
          <instructionId>scriptTable_13_4/scriptTable_9_0</instructionId>
          <col>1</col>
          <row>1</row>
          <type>ArgumentExpectation</type>
                                        <evaluationMessage><![CDATA[]]></evaluationMessage>
                  </expectation>
                <expectation>
          <status>ignored</status>
          <instructionId>scriptTable_13_4/scriptTable_9_0</instructionId>
          <col>0</col>
          <row>1</row>
          <type>ScriptActionExpectation</type>
                    <actual><![CDATA[!error:Method execute[1] not found in com.statefarm.rpn.fixtures.RpnCalculatorFixture.]]></actual>
                              <expected><![CDATA[execute]]></expected>
                              <evaluationMessage><![CDATA[execute error(Method execute[1] not found in com.statefarm.rpn.fixtures.RpnCalculatorFixture.)]]></evaluationMessage>
                  </expectation>
        
      </instructionResult>
            <instructionResult>
        <instruction><![CDATA[[scriptTable_13_5/scriptTable_10_0, call, scriptTableActor, xRegister]]]></instruction>
        <slimResult><![CDATA[!error:Method xRegister[0] not found in com.statefarm.rpn.fixtures.RpnCalculatorFixture.]]></slimResult>
                <expectation>
          <status>ignored</status>
          <instructionId>scriptTable_13_5/scriptTable_10_0</instructionId>
          <col>2</col>
          <row>1</row>
          <type>ReturnedValueExpectation</type>
                    <actual><![CDATA[!error:Method xRegister[0] not found in com.statefarm.rpn.fixtures.RpnCalculatorFixture.]]></actual>
                              <expected><![CDATA[0.25]]></expected>
                              <evaluationMessage><![CDATA[0.25 error(Method xRegister[0] not found in com.statefarm.rpn.fixtures.RpnCalculatorFixture.)]]></evaluationMessage>
                  </expectation>
        
      </instructionResult>
      
    </instructions>
    
  </result>
  
  
  <finalCounts>
    <right>0</right>
    <wrong>0</wrong>
    <ignores>0</ignores>
    <exceptions>0</exceptions>
  </finalCounts>
  
</testResults>

